pyutplugins/ExternalTypes.py
pyutplugins/IPluginAdapter.py
pyutplugins/PluginManager.py
pyutplugins/__init__.py
pyutplugins/_version.py
pyutplugins/py.typed
pyutplugins/common/Common.py
pyutplugins/common/ElementTreeData.py
pyutplugins/common/LinkMakerMixin.py
pyutplugins/common/PluginTypes.py
pyutplugins/common/__init__.py
pyutplugins/common/py.typed
pyutplugins/common/ui/BaseEditDialog.py
pyutplugins/common/ui/__init__.py
pyutplugins/common/ui/py.typed
pyutplugins/common/ui/preferences/PluginPreferencesPage.py
pyutplugins/common/ui/preferences/__init__.py
pyutplugins/common/ui/preferences/py.typed
pyutplugins/exceptions/AbstractMethodNotImplementedException.py
pyutplugins/exceptions/InvalidPluginExtensionException.py
pyutplugins/exceptions/InvalidPluginNameException.py
pyutplugins/exceptions/__init__.py
pyutplugins/exceptions/py.typed
pyutplugins/ioplugins/IOAscii.py
pyutplugins/ioplugins/IODTD.py
pyutplugins/ioplugins/IOGML.py
pyutplugins/ioplugins/IOJava.py
pyutplugins/ioplugins/IOMermaid.py
pyutplugins/ioplugins/IOPdf.py
pyutplugins/ioplugins/IOPython.py
pyutplugins/ioplugins/IOWxImage.py
pyutplugins/ioplugins/IOXml.py
pyutplugins/ioplugins/__init__.py
pyutplugins/ioplugins/py.typed
pyutplugins/ioplugins/dtd/DTDAttribute.py
pyutplugins/ioplugins/dtd/DTDElementTypes.py
pyutplugins/ioplugins/dtd/DTDParser.py
pyutplugins/ioplugins/dtd/__init__.py
pyutplugins/ioplugins/dtd/py.typed
pyutplugins/ioplugins/gml/GMLExporter.py
pyutplugins/ioplugins/gml/UnsupportedOperation.py
pyutplugins/ioplugins/gml/__init__.py
pyutplugins/ioplugins/gml/py.typed
pyutplugins/ioplugins/java/JavaReader.py
pyutplugins/ioplugins/java/JavaWriter.py
pyutplugins/ioplugins/java/__init__.py
pyutplugins/ioplugins/java/py.typed
pyutplugins/ioplugins/mermaid/MermaidDirection.py
pyutplugins/ioplugins/mermaid/MermaidWriter.py
pyutplugins/ioplugins/mermaid/__init__.py
pyutplugins/ioplugins/mermaid/py.typed
pyutplugins/ioplugins/python/DlgSelectMultiplePackages.py
pyutplugins-3.2.6.dist-info/LICENSE
pyutplugins-3.2.6.dist-info/METADATA
pyutplugins-3.2.6.dist-info/WHEEL
pyutplugins-3.2.6.dist-info/top_level.txt
pyutplugins-3.2.6.dist-info/RECORD
