Metadata-Version: 2.2
Name: pyutplugins
Version: 3.2.6
Summary: Pyut Plugins
Author-email: "Humberto A. Sanchez II" <Humbert.A.Sanchez.II@gmail.com>
Maintainer-email: "Humberto A. Sanchez II" <Humbert.A.Sanchez.II@gmail.com>
License: GNU AFFERO GENERAL PUBLIC LICENSE
Project-URL: Repository, https://github.com/hasii2011/pyutplugins
Keywords: pyut,python,plugin
Classifier: Programming Language :: Python
Classifier: Intended Audience :: Developers
Classifier: License :: OSI Approved :: GNU Affero General Public License v3
Classifier: Operating System :: MacOS :: MacOS X
Classifier: Topic :: Software Development :: Libraries :: Python Modules
License-File: LICENSE
Requires-Dist: codeallybasic>=1.10.0
Requires-Dist: codeallyadvanced>=1.4.2
Requires-Dist: pyutmodelv2>=2.2.3
Requires-Dist: ogl>=3.6.7
Requires-Dist: oglio>=2.4.0
Requires-Dist: wxPython>=4.2.2
Requires-Dist: antlr4-python3-runtime==4.13.1
Requires-Dist: orthogonal>=1.3.1
Requires-Dist: pyforcedirectedlayout>=0.80.6
Requires-Dist: pyorthogonalrouting>=1.4.1
Requires-Dist: pyimage2pdf>=1.0.3
Provides-Extra: test
Requires-Dist: html-testRunner~=1.2.1; extra == "test"
Requires-Dist: buildlackey==1.7.0; extra == "test"
Requires-Dist: mypy==1.14.0; extra == "test"
Requires-Dist: mypy-extensions==1.0.0; extra == "test"
Requires-Dist: typing_extensions==4.10.0; extra == "test"
Requires-Dist: types-Deprecated==1.2.9.20240311; extra == "test"
Requires-Dist: click==8.1.8; extra == "test"
Provides-Extra: deploy
Requires-Dist: wheel==0.45.1; extra == "deploy"
Requires-Dist: setuptools==75.7.0; extra == "deploy"
Requires-Dist: twine==6.0.1; extra == "deploy"
Requires-Dist: build==1.2.2.post1; extra == "deploy"
